{
  "title": "2019年4月（共43部）",
  "subjects": [
    {
      "images": {
        "grid": "https://lain.bgm.tv/r/100/pic/cover/l/37/75/231247_1Cc81.jpg",
        "common": "https://lain.bgm.tv/r/400/pic/cover/l/37/75/231247_1Cc81.jpg"
      },
      "name": "ULTRAMAN",
      "name_cn": "机动奥特曼",
      "infobox": [
        {
          "key": "放送星期",
          "value": "星期一"
        }
      ],
      "rating": {
        "rank": 6095,
        "total": 1623,
        "count": {
          "1": 6,
          "2": 7,
          "3": 23,
          "4": 56,
          "5": 190,
          "6": 610,
          "7": 566,
          "8": 146,
          "9": 11,
          "10": 8
        },
        "score": 6.3
      },
      "total_episodes": 13,
      "collection": {
        "on_hold": 107,
        "dropped": 183,
        "wish": 195,
        "collect": 2481,
        "doing": 115
      },
      "id": 231247,
      "meta_tags": [
        "漫画改",
        "战斗",
        "WEB"
      ],
      "nsfw": false,
      "episodes_summary": {
        "aired_episodes": 13,
        "total_comments": 185,
        "episodes": [
          {
            "ep": 1,
            "comments": 19
          },
          {
            "ep": 2,
            "comments": 20
          },
          {
            "ep": 3,
            "comments": 13
          },
          {
            "ep": 4,
            "comments": 15
          },
          {
            "ep": 5,
            "comments": 12
          },
          {
            "ep": 6,
            "comments": 13
          },
          {
            "ep": 7,
            "comments": 18
          },
          {
            "ep": 8,
            "comments": 20
          },
          {
            "ep": 9,
            "comments": 13
          },
          {
            "ep": 10,
            "comments": 6
          },
          {
            "ep": 11,
            "comments": 15
          },
          {
            "ep": 12,
            "comments": 9
          },
          {
            "ep": 13,
            "comments": 12
          }
        ]
      }
    },
    {
      "images": {
        "grid": "https://lain.bgm.tv/r/100/pic/cover/l/7f/b2/267615_Qio7E.jpg",
        "common": "https://lain.bgm.tv/r/400/pic/cover/l/7f/b2/267615_Qio7E.jpg"
      },
      "name": "ダイヤのA actⅡ",
      "name_cn": "钻石王牌 act2",
      "infobox": [
        {
          "key": "放送星期",
          "value": "星期二"
        }
      ],
      "rating": {
        "rank": 1370,
        "total": 511,
        "count": {
          "1": 2,
          "2": 2,
          "3": 1,
          "4": 9,
          "5": 21,
          "6": 64,
          "7": 175,
          "8": 174,
          "9": 33,
          "10": 30
        },
        "score": 7.3
      },
      "total_episodes": 52,
      "collection": {
        "on_hold": 43,
        "dropped": 48,
        "wish": 157,
        "collect": 730,
        "doing": 95
      },
      "id": 267615,
      "meta_tags": [
        "TV",
        "日本",
        "运动",
        "漫画改"
      ],
      "nsfw": false,
      "episodes_summary": {
        "aired_episodes": 52,
        "total_comments": 541,
        "episodes": [
          {
            "ep": 1,
            "comments": 19
          },
          {
            "ep": 2,
            "comments": 16
          },
          {
            "ep": 3,
            "comments": 18
          },
          {
            "ep": 4,
            "comments": 22
          },
          {
            "ep": 5,
            "comments": 14
          },
          {
            "ep": 6,
            "comments": 8
          },
          {
            "ep": 7,
            "comments": 23
          },
          {
            "ep": 8,
            "comments": 12
          },
          {
            "ep": 9,
            "comments": 10
          },
          {
            "ep": 10,
            "comments": 14
          },
          {
            "ep": 11,
            "comments": 9
          },
          {
            "ep": 12,
            "comments": 16
          },
          {
            "ep": 13,
            "comments": 10
          },
          {
            "ep": 14,
            "comments": 9
          },
          {
            "ep": 15,
            "comments": 21
          },
          {
            "ep": 16,
            "comments": 12
          },
          {
            "ep": 17,
            "comments": 14
          },
          {
            "ep": 18,
            "comments": 8
          },
          {
            "ep": 19,
            "comments": 7
          },
          {
            "ep": 20,
            "comments": 7
          },
          {
            "ep": 21,
            "comments": 7
          },
          {
            "ep": 22,
            "comments": 11
          },
          {
            "ep": 23,
            "comments": 3
          },
          {
            "ep": 24,
            "comments": 8
          },
          {
            "ep": 25,
            "comments": 10
          },
          {
            "ep": 26,
            "comments": 13
          },
          {
            "ep": 27,
            "comments": 9
          },
          {
            "ep": 28,
            "comments": 6
          },
          {
            "ep": 29,
            "comments": 5
          },
          {
            "ep": 30,
            "comments": 14
          },
          {
            "ep": 31,
            "comments": 6
          },
          {
            "ep": 32,
            "comments": 3
          },
          {
            "ep": 33,
            "comments": 5
          },
          {
            "ep": 34,
            "comments": 4
          },
          {
            "ep": 35,
            "comments": 10
          },
          {
            "ep": 36,
            "comments": 7
          },
          {
            "ep": 37,
            "comments": 15
          },
          {
            "ep": 38,
            "comments": 4
          },
          {
            "ep": 39,
            "comments": 12
          },
          {
            "ep": 40,
            "comments": 8
          },
          {
            "ep": 41,
            "comments": 7
          },
          {
            "ep": 42,
            "comments": 6
          },
          {
            "ep": 43,
            "comments": 7
          },
          {
            "ep": 44,
            "comments": 4
          },
          {
            "ep": 45,
            "comments": 26
          },
          {
            "ep": 46,
            "comments": 4
          },
          {
            "ep": 47,
            "comments": 14
          },
          {
            "ep": 48,
            "comments": 12
          },
          {
            "ep": 49,
            "comments": 8
          },
          {
            "ep": 50,
            "comments": 4
          },
          {
            "ep": 51,
            "comments": 10
          },
          {
            "ep": 52,
            "comments": 10
          }
        ]
      }
    },
    {
      "images": {
        "grid": "https://lain.bgm.tv/r/100/pic/cover/l/f2/28/268320_wRhYU.jpg",
        "common": "https://lain.bgm.tv/r/400/pic/cover/l/f2/28/268320_wRhYU.jpg"
      },
      "name": "アイドルマスター シンデレラガールズ劇場 CLIMAX SEASON",
      "name_cn": "偶像大师 灰姑娘女孩剧场 高潮季",
      "infobox": [
        {
          "key": "放送星期",
          "value": "星期二"
        }
      ],
      "rating": {
        "rank": 3955,
        "total": 348,
        "count": {
          "1": 0,
          "2": 2,
          "3": 1,
          "4": 7,
          "5": 30,
          "6": 104,
          "7": 139,
          "8": 57,
          "9": 4,
          "10": 4
        },
        "score": 6.6
      },
      "total_episodes": 16,
      "collection": {
        "on_hold": 26,
        "dropped": 27,
        "wish": 177,
        "collect": 596,
        "doing": 46
      },
      "id": 268320,
      "meta_tags": [
        "TV",
        "日本",
        "游戏改"
      ],
      "nsfw": false,
      "episodes_summary": {
        "aired_episodes": 13,
        "total_comments": 78,
        "episodes": [
          {
            "ep": 1,
            "comments": 6
          },
          {
            "ep": 2,
            "comments": 5
          },
          {
            "ep": 3,
            "comments": 6
          },
          {
            "ep": 4,
            "comments": 5
          },
          {
            "ep": 5,
            "comments": 6
          },
          {
            "ep": 6,
            "comments": 8
          },
          {
            "ep": 7,
            "comments": 5
          },
          {
            "ep": 8,
            "comments": 5
          },
          {
            "ep": 9,
            "comments": 7
          },
          {
            "ep": 10,
            "comments": 5
          },
          {
            "ep": 11,
            "comments": 6
          },
          {
            "ep": 12,
            "comments": 9
          },
          {
            "ep": 13,
            "comments": 5
          }
        ]
      }
    },
    {
      "images": {
        "grid": "https://lain.bgm.tv/r/100/pic/cover/l/66/f5/204135_LubD7.jpg",
        "common": "https://lain.bgm.tv/r/400/pic/cover/l/66/f5/204135_LubD7.jpg"
      },
      "name": "この世の果てで恋を唄う少女YU-NO",
      "name_cn": "在世界尽头咏唱恋曲的少女YU-NO",
      "infobox": [
        {
          "key": "放送星期",
          "value": "星期二"
        }
      ],
      "rating": {
        "rank": 8393,
        "total": 1228,
        "count": {
          "1": 38,
          "2": 18,
          "3": 72,
          "4": 143,
          "5": 254,
          "6": 373,
          "7": 218,
          "8": 79,
          "9": 17,
          "10": 16
        },
        "score": 5.6
      },
      "total_episodes": 28,
      "collection": {
        "on_hold": 321,
        "dropped": 423,
        "wish": 742,
        "collect": 1610,
        "doing": 344
      },
      "id": 204135,
      "meta_tags": [
        "科幻",
        "TV",
        "日本",
        "游戏改"
      ],
      "nsfw": false,
      "episodes_summary": {
        "aired_episodes": 26,
        "total_comments": 850,
        "episodes": [
          {
            "ep": 1,
            "comments": 72
          },
          {
            "ep": 2,
            "comments": 50
          },
          {
            "ep": 3,
            "comments": 29
          },
          {
            "ep": 4,
            "comments": 63
          },
          {
            "ep": 5,
            "comments": 53
          },
          {
            "ep": 6,
            "comments": 43
          },
          {
            "ep": 7,
            "comments": 20
          },
          {
            "ep": 8,
            "comments": 31
          },
          {
            "ep": 9,
            "comments": 26
          },
          {
            "ep": 10,
            "comments": 38
          },
          {
            "ep": 11,
            "comments": 35
          },
          {
            "ep": 12,
            "comments": 24
          },
          {
            "ep": 13,
            "comments": 31
          },
          {
            "ep": 14,
            "comments": 28
          },
          {
            "ep": 15,
            "comments": 26
          },
          {
            "ep": 16,
            "comments": 19
          },
          {
            "ep": 17,
            "comments": 29
          },
          {
            "ep": 18,
            "comments": 35
          },
          {
            "ep": 19,
            "comments": 27
          },
          {
            "ep": 20,
            "comments": 23
          },
          {
            "ep": 21,
            "comments": 15
          },
          {
            "ep": 22,
            "comments": 36
          },
          {
            "ep": 23,
            "comments": 21
          },
          {
            "ep": 24,
            "comments": 30
          },
          {
            "ep": 25,
            "comments": 17
          },
          {
            "ep": 26,
            "comments": 29
          }
        ]
      }
    },
    {
      "images": {
        "grid": "https://lain.bgm.tv/r/100/pic/cover/l/63/0f/193619_MLNLZ.jpg",
        "common": "https://lain.bgm.tv/r/400/pic/cover/l/63/0f/193619_MLNLZ.jpg"
      },
      "name": "ワンパンマン 第2期",
      "name_cn": "一拳超人 第二季",
      "infobox": [
        {
          "key": "放送星期",
          "value": "星期二"
        }
      ],
      "rating": {
        "rank": 5225,
        "total": 7116,
        "count": {
          "1": 21,
          "2": 26,
          "3": 73,
          "4": 242,
          "5": 689,
          "6": 2351,
          "7": 2705,
          "8": 807,
          "9": 89,
          "10": 113
        },
        "score": 6.5
      },
      "total_episodes": 19,
      "collection": {
        "on_hold": 247,
        "dropped": 285,
        "wish": 764,
        "collect": 11735,
        "doing": 456
      },
      "id": 193619,
      "meta_tags": [
        "TV",
        "日本",
        "奇幻",
        "漫画改",
        "战斗"
      ],
      "nsfw": false,
      "episodes_summary": {
        "aired_episodes": 12,
        "total_comments": 765,
        "episodes": [
          {
            "ep": 1,
            "comments": 92
          },
          {
            "ep": 2,
            "comments": 116
          },
          {
            "ep": 3,
            "comments": 80
          },
          {
            "ep": 4,
            "comments": 35
          },
          {
            "ep": 5,
            "comments": 47
          },
          {
            "ep": 6,
            "comments": 44
          },
          {
            "ep": 7,
            "comments": 53
          },
          {
            "ep": 8,
            "comments": 72
          },
          {
            "ep": 9,
            "comments": 70
          },
          {
            "ep": 10,
            "comments": 40
          },
          {
            "ep": 11,
            "comments": 54
          },
          {
            "ep": 12,
            "comments": 62
          }
        ]
      }
    },
    {
      "images": {
        "grid": "https://lain.bgm.tv/r/100/pic/cover/l/e2/ed/272921_Wkee1.jpg",
        "common": "https://lain.bgm.tv/r/400/pic/cover/l/e2/ed/272921_Wkee1.jpg"
      },
      "name": "アイカツフレンズ！～かがやきのジュエル～",
      "name_cn": "偶像活动Friends ～闪耀的宝石～",
      "infobox": [
        {
          "key": "放送星期",
          "value": "星期四"
        }
      ],
      "rating": {
        "rank": 4474,
        "total": 97,
        "count": {
          "1": 0,
          "2": 0,
          "3": 1,
          "4": 6,
          "5": 22,
          "6": 22,
          "7": 27,
          "8": 13,
          "9": 3,
          "10": 3
        },
        "score": 6.4
      },
      "total_episodes": 26,
      "collection": {
        "on_hold": 13,
        "dropped": 22,
        "wish": 54,
        "collect": 128,
        "doing": 19
      },
      "id": 272921,
      "meta_tags": [
        "TV",
        "日本",
        "原创"
      ],
      "nsfw": false,
      "episodes_summary": {
        "aired_episodes": 26,
        "total_comments": 163,
        "episodes": [
          {
            "ep": 1,
            "comments": 11
          },
          {
            "ep": 2,
            "comments": 7
          },
          {
            "ep": 3,
            "comments": 7
          },
          {
            "ep": 4,
            "comments": 5
          },
          {
            "ep": 5,
            "comments": 8
          },
          {
            "ep": 6,
            "comments": 6
          },
          {
            "ep": 7,
            "comments": 2
          },
          {
            "ep": 8,
            "comments": 5
          },
          {
            "ep": 9,
            "comments": 8
          },
          {
            "ep": 10,
            "comments": 6
          },
          {
            "ep": 11,
            "comments": 11
          },
          {
            "ep": 12,
            "comments": 4
          },
          {
            "ep": 13,
            "comments": 2
          },
          {
            "ep": 14,
            "comments": 3
          },
          {
            "ep": 15,
            "comments": 5
          },
          {
            "ep": 16,
            "comments": 5
          },
          {
            "ep": 17,
            "comments": 7
          },
          {
            "ep": 18,
            "comments": 8
          },
          {
            "ep": 19,
            "comments": 4
          },
          {
            "ep": 20,
            "comments": 9
          },
          {
            "ep": 21,
            "comments": 9
          },
          {
            "ep": 22,
            "comments": 4
          },
          {
            "ep": 23,
            "comments": 7
          },
          {
            "ep": 24,
            "comments": 4
          },
          {
            "ep": 25,
            "comments": 9
          },
          {
            "ep": 26,
            "comments": 7
          }
        ]
      }
    },
    {
      "images": {
        "grid": "https://lain.bgm.tv/r/100/pic/cover/l/55/38/247841_445ID.jpg",
        "common": "https://lain.bgm.tv/r/400/pic/cover/l/55/38/247841_445ID.jpg"
      },
      "name": "八十亀ちゃんかんさつにっき",
      "name_cn": "八十龟酱观察日记",
      "infobox": [
        {
          "key": "放送星期",
          "value": "星期四"
        }
      ],
      "rating": {
        "rank": 6149,
        "total": 242,
        "count": {
          "1": 1,
          "2": 0,
          "3": 0,
          "4": 6,
          "5": 49,
          "6": 99,
          "7": 72,
          "8": 13,
          "9": 2,
          "10": 0
        },
        "score": 6.2
      },
      "total_episodes": 12,
      "collection": {
        "on_hold": 42,
        "dropped": 53,
        "wish": 154,
        "collect": 394,
        "doing": 41
      },
      "id": 247841,
      "meta_tags": [
        "TV",
        "日本",
        "漫画改"
      ],
      "nsfw": false,
      "episodes_summary": {
        "aired_episodes": 12,
        "total_comments": 64,
        "episodes": [
          {
            "ep": 1,
            "comments": 10
          },
          {
            "ep": 2,
            "comments": 6
          },
          {
            "ep": 3,
            "comments": 1
          },
          {
            "ep": 4,
            "comments": 2
          },
          {
            "ep": 5,
            "comments": 2
          },
          {
            "ep": 6,
            "comments": 4
          },
          {
            "ep": 7,
            "comments": 2
          },
          {
            "ep": 8,
            "comments": 6
          },
          {
            "ep": 9,
            "comments": 6
          },
          {
            "ep": 10,
            "comments": 8
          },
          {
            "ep": 11,
            "comments": 4
          },
          {
            "ep": 12,
            "comments": 13
          }
        ]
      }
    },
    {
      "images": {
        "grid": "https://lain.bgm.tv/r/100/pic/cover/l/77/c0/261048_w8T9t.jpg",
        "common": "https://lain.bgm.tv/r/400/pic/cover/l/77/c0/261048_w8T9t.jpg"
      },
      "name": "叛逆性ミリオンアーサー 第2シーズン",
      "name_cn": "叛逆性百万亚瑟王 第二季",
      "infobox": [
        {
          "key": "放送星期",
          "value": "星期四"
        }
      ],
      "rating": {
        "rank": 6237,
        "total": 225,
        "count": {
          "1": 3,
          "2": 1,
          "3": 3,
          "4": 10,
          "5": 42,
          "6": 78,
          "7": 67,
          "8": 15,
          "9": 3,
          "10": 3
        },
        "score": 6.1
      },
      "total_episodes": 14,
      "collection": {
        "on_hold": 32,
        "dropped": 38,
        "wish": 133,
        "collect": 389,
        "doing": 44
      },
      "id": 261048,
      "meta_tags": [
        "TV",
        "日本",
        "游戏改"
      ],
      "nsfw": false,
      "episodes_summary": {
        "aired_episodes": 13,
        "total_comments": 90,
        "episodes": [
          {
            "ep": 1,
            "comments": 9
          },
          {
            "ep": 2,
            "comments": 6
          },
          {
            "ep": 3,
            "comments": 6
          },
          {
            "ep": 4,
            "comments": 8
          },
          {
            "ep": 5,
            "comments": 9
          },
          {
            "ep": 6,
            "comments": 10
          },
          {
            "ep": 7,
            "comments": 8
          },
          {
            "ep": 8,
            "comments": 6
          },
          {
            "ep": 9,
            "comments": 5
          },
          {
            "ep": 10,
            "comments": 6
          },
          {
            "ep": 11,
            "comments": 7
          },
          {
            "ep": 12,
            "comments": 5
          },
          {
            "ep": 13,
            "comments": 5
          }
        ]
      }
    },
    {
      "images": {
        "grid": "https://lain.bgm.tv/r/100/pic/cover/l/72/ec/269824_48U08.jpg",
        "common": "https://lain.bgm.tv/r/400/pic/cover/l/72/ec/269824_48U08.jpg"
      },
      "name": "BAKUMATSUクライシス",
      "name_cn": "恋爱幕末男友外传～在时空的彼方盛开之恋～CRISIS",
      "infobox": [
        {
          "key": "放送星期",
          "value": "星期四"
        }
      ],
      "rating": {
        "rank": 0,
        "total": 19,
        "count": {
          "1": 2,
          "2": 0,
          "3": 4,
          "4": 1,
          "5": 4,
          "6": 0,
          "7": 5,
          "8": 3,
          "9": 0,
          "10": 0
        },
        "score": 5.1
      },
      "total_episodes": 12,
      "collection": {
        "on_hold": 10,
        "dropped": 27,
        "wish": 49,
        "collect": 25,
        "doing": 5
      },
      "id": 269824,
      "meta_tags": [
        "TV",
        "日本",
        "游戏改"
      ],
      "nsfw": false,
      "episodes_summary": {
        "aired_episodes": 12,
        "total_comments": 15,
        "episodes": [
          {
            "ep": 1,
            "comments": 2
          },
          {
            "ep": 2,
            "comments": 2
          },
          {
            "ep": 3,
            "comments": 0
          },
          {
            "ep": 4,
            "comments": 2
          },
          {
            "ep": 5,
            "comments": 1
          },
          {
            "ep": 6,
            "comments": 2
          },
          {
            "ep": 7,
            "comments": 1
          },
          {
            "ep": 8,
            "comments": 0
          },
          {
            "ep": 9,
            "comments": 1
          },
          {
            "ep": 10,
            "comments": 1
          },
          {
            "ep": 11,
            "comments": 2
          },
          {
            "ep": 12,
            "comments": 1
          }
        ]
      }
    },
    {
      "images": {
        "grid": "https://lain.bgm.tv/r/100/pic/cover/l/20/f2/266455_fRBdM.jpg",
        "common": "https://lain.bgm.tv/r/400/pic/cover/l/20/f2/266455_fRBdM.jpg"
      },
      "name": "フルーツバスケット 1st season",
      "name_cn": "水果篮子 第一季",
      "infobox": [
        {
          "key": "放送星期",
          "value": "星期五"
        }
      ],
      "rating": {
        "rank": 2317,
        "total": 1416,
        "count": {
          "1": 3,
          "2": 4,
          "3": 5,
          "4": 19,
          "5": 73,
          "6": 282,
          "7": 543,
          "8": 389,
          "9": 62,
          "10": 36
        },
        "score": 7.1
      },
      "total_episodes": 25,
      "collection": {
        "on_hold": 401,
        "dropped": 327,
        "wish": 1140,
        "collect": 2122,
        "doing": 442
      },
      "id": 266455,
      "meta_tags": [
        "TV",
        "恋爱",
        "日本",
        "漫画改",
        "乙女"
      ],
      "nsfw": false,
      "episodes_summary": {
        "aired_episodes": 25,
        "total_comments": 569,
        "episodes": [
          {
            "ep": 1,
            "comments": 49
          },
          {
            "ep": 2,
            "comments": 24
          },
          {
            "ep": 3,
            "comments": 26
          },
          {
            "ep": 4,
            "comments": 29
          },
          {
            "ep": 5,
            "comments": 35
          },
          {
            "ep": 6,
            "comments": 17
          },
          {
            "ep": 7,
            "comments": 26
          },
          {
            "ep": 8,
            "comments": 16
          },
          {
            "ep": 9,
            "comments": 18
          },
          {
            "ep": 10,
            "comments": 13
          },
          {
            "ep": 11,
            "comments": 19
          },
          {
            "ep": 12,
            "comments": 15
          },
          {
            "ep": 13,
            "comments": 19
          },
          {
            "ep": 14,
            "comments": 32
          },
          {
            "ep": 15,
            "comments": 18
          },
          {
            "ep": 16,
            "comments": 15
          },
          {
            "ep": 17,
            "comments": 26
          },
          {
            "ep": 18,
            "comments": 25
          },
          {
            "ep": 19,
            "comments": 19
          },
          {
            "ep": 20,
            "comments": 26
          },
          {
            "ep": 21,
            "comments": 21
          },
          {
            "ep": 22,
            "comments": 24
          },
          {
            "ep": 23,
            "comments": 10
          },
          {
            "ep": 24,
            "comments": 31
          },
          {
            "ep": 25,
            "comments": 16
          }
        ]
      }
    },
    {
      "images": {
        "grid": "https://lain.bgm.tv/r/100/pic/cover/l/b4/fb/268510_XKKrF.jpg",
        "common": "https://lain.bgm.tv/r/400/pic/cover/l/b4/fb/268510_XKKrF.jpg"
      },
      "name": "川柳少女",
      "name_cn": "川柳少女",
      "infobox": [
        {
          "key": "放送星期",
          "value": "星期五"
        }
      ],
      "rating": {
        "rank": 4928,
        "total": 3775,
        "count": {
          "1": 4,
          "2": 6,
          "3": 17,
          "4": 53,
          "5": 366,
          "6": 1332,
          "7": 1516,
          "8": 401,
          "9": 35,
          "10": 45
        },
        "score": 6.5
      },
      "total_episodes": 12,
      "collection": {
        "on_hold": 443,
        "dropped": 513,
        "wish": 912,
        "collect": 6204,
        "doing": 571
      },
      "id": 268510,
      "meta_tags": [
        "校园",
        "TV",
        "恋爱",
        "日本",
        "漫画改"
      ],
      "nsfw": false,
      "episodes_summary": {
        "aired_episodes": 12,
        "total_comments": 348,
        "episodes": [
          {
            "ep": 1,
            "comments": 60
          },
          {
            "ep": 2,
            "comments": 29
          },
          {
            "ep": 3,
            "comments": 42
          },
          {
            "ep": 4,
            "comments": 34
          },
          {
            "ep": 5,
            "comments": 29
          },
          {
            "ep": 6,
            "comments": 30
          },
          {
            "ep": 7,
            "comments": 25
          },
          {
            "ep": 8,
            "comments": 19
          },
          {
            "ep": 9,
            "comments": 21
          },
          {
            "ep": 10,
            "comments": 17
          },
          {
            "ep": 11,
            "comments": 21
          },
          {
            "ep": 12,
            "comments": 21
          }
        ]
      }
    },
    {
      "images": {
        "grid": "https://lain.bgm.tv/r/100/pic/cover/l/7d/87/268412_P63Pf.jpg",
        "common": "https://lain.bgm.tv/r/400/pic/cover/l/7d/87/268412_P63Pf.jpg"
      },
      "name": "みだらな青ちゃんは勉強ができない",
      "name_cn": "淫乱的青酱不能学习",
      "infobox": [
        {
          "key": "放送星期",
          "value": "星期五"
        }
      ],
      "rating": {
        "rank": 6584,
        "total": 3037,
        "count": {
          "1": 14,
          "2": 20,
          "3": 37,
          "4": 101,
          "5": 445,
          "6": 1271,
          "7": 866,
          "8": 217,
          "9": 27,
          "10": 39
        },
        "score": 6.2
      },
      "total_episodes": 12,
      "collection": {
        "on_hold": 388,
        "dropped": 444,
        "wish": 1242,
        "collect": 4916,
        "doing": 401
      },
      "id": 268412,
      "meta_tags": [
        "校园",
        "TV",
        "恋爱",
        "日本",
        "漫画改"
      ],
      "nsfw": false,
      "episodes_summary": {
        "aired_episodes": 12,
        "total_comments": 355,
        "episodes": [
          {
            "ep": 1,
            "comments": 55
          },
          {
            "ep": 2,
            "comments": 41
          },
          {
            "ep": 3,
            "comments": 28
          },
          {
            "ep": 4,
            "comments": 22
          },
          {
            "ep": 5,
            "comments": 24
          },
          {
            "ep": 6,
            "comments": 28
          },
          {
            "ep": 7,
            "comments": 24
          },
          {
            "ep": 8,
            "comments": 31
          },
          {
            "ep": 9,
            "comments": 23
          },
          {
            "ep": 10,
            "comments": 24
          },
          {
            "ep": 11,
            "comments": 23
          },
          {
            "ep": 12,
            "comments": 32
          }
        ]
      }
    },
    {
      "images": {
        "grid": "https://lain.bgm.tv/r/100/pic/cover/l/9f/ab/241335_sLGll.jpg",
        "common": "https://lain.bgm.tv/r/400/pic/cover/l/9f/ab/241335_sLGll.jpg"
      },
      "name": "ひとりぼっちの○○生活",
      "name_cn": "一个人的○○小日子",
      "infobox": [
        {
          "key": "放送星期",
          "value": "星期五"
        }
      ],
      "rating": {
        "rank": 4334,
        "total": 2173,
        "count": {
          "1": 2,
          "2": 5,
          "3": 4,
          "4": 36,
          "5": 180,
          "6": 708,
          "7": 885,
          "8": 296,
          "9": 37,
          "10": 20
        },
        "score": 6.6
      },
      "total_episodes": 12,
      "collection": {
        "on_hold": 300,
        "dropped": 393,
        "wish": 786,
        "collect": 3574,
        "doing": 357
      },
      "id": 241335,
      "meta_tags": [
        "百合",
        "TV",
        "日本",
        "漫画改",
        "日常"
      ],
      "nsfw": false,
      "episodes_summary": {
        "aired_episodes": 12,
        "total_comments": 433,
        "episodes": [
          {
            "ep": 1,
            "comments": 67
          },
          {
            "ep": 2,
            "comments": 38
          },
          {
            "ep": 3,
            "comments": 40
          },
          {
            "ep": 4,
            "comments": 29
          },
          {
            "ep": 5,
            "comments": 40
          },
          {
            "ep": 6,
            "comments": 41
          },
          {
            "ep": 7,
            "comments": 37
          },
          {
            "ep": 8,
            "comments": 31
          },
          {
            "ep": 9,
            "comments": 29
          },
          {
            "ep": 10,
            "comments": 29
          },
          {
            "ep": 11,
            "comments": 25
          },
          {
            "ep": 12,
            "comments": 27
          }
        ]
      }
    },
    {
      "images": {
        "grid": "https://lain.bgm.tv/r/100/pic/cover/l/ed/05/274716_0JiCr.jpg",
        "common": "https://lain.bgm.tv/r/400/pic/cover/l/ed/05/274716_0JiCr.jpg"
      },
      "name": "ベイブレードバースト ガチ",
      "name_cn": "霸旋陀螺 爆刃对决 GT",
      "infobox": [
        {
          "key": "放送星期",
          "value": "五"
        }
      ],
      "rating": {
        "rank": 0,
        "total": 5,
        "count": {
          "1": 0,
          "2": 0,
          "3": 0,
          "4": 0,
          "5": 1,
          "6": 0,
          "7": 2,
          "8": 0,
          "9": 1,
          "10": 1
        },
        "score": 7.6
      },
      "total_episodes": 52,
      "collection": {
        "on_hold": 5,
        "dropped": 10,
        "wish": 8,
        "collect": 9,
        "doing": 3
      },
      "id": 274716,
      "meta_tags": [
        "WEB"
      ],
      "nsfw": false,
      "episodes_summary": {
        "aired_episodes": 52,
        "total_comments": 0,
        "episodes": [
          {
            "ep": 1,
            "comments": 0
          },
          {
            "ep": 2,
            "comments": 0
          },
          {
            "ep": 3,
            "comments": 0
          },
          {
            "ep": 4,
            "comments": 0
          },
          {
            "ep": 5,
            "comments": 0
          },
          {
            "ep": 6,
            "comments": 0
          },
          {
            "ep": 7,
            "comments": 0
          },
          {
            "ep": 8,
            "comments": 0
          },
          {
            "ep": 9,
            "comments": 0
          },
          {
            "ep": 10,
            "comments": 0
          },
          {
            "ep": 11,
            "comments": 0
          },
          {
            "ep": 12,
            "comments": 0
          },
          {
            "ep": 13,
            "comments": 0
          },
          {
            "ep": 14,
            "comments": 0
          },
          {
            "ep": 15,
            "comments": 0
          },
          {
            "ep": 16,
            "comments": 0
          },
          {
            "ep": 17,
            "comments": 0
          },
          {
            "ep": 18,
            "comments": 0
          },
          {
            "ep": 19,
            "comments": 0
          },
          {
            "ep": 20,
            "comments": 0
          },
          {
            "ep": 21,
            "comments": 0
          },
          {
            "ep": 22,
            "comments": 0
          },
          {
            "ep": 23,
            "comments": 0
          },
          {
            "ep": 24,
            "comments": 0
          },
          {
            "ep": 25,
            "comments": 0
          },
          {
            "ep": 26,
            "comments": 0
          },
          {
            "ep": 27,
            "comments": 0
          },
          {
            "ep": 28,
            "comments": 0
          },
          {
            "ep": 29,
            "comments": 0
          },
          {
            "ep": 30,
            "comments": 0
          },
          {
            "ep": 31,
            "comments": 0
          },
          {
            "ep": 32,
            "comments": 0
          },
          {
            "ep": 33,
            "comments": 0
          },
          {
            "ep": 34,
            "comments": 0
          },
          {
            "ep": 35,
            "comments": 0
          },
          {
            "ep": 36,
            "comments": 0
          },
          {
            "ep": 37,
            "comments": 0
          },
          {
            "ep": 38,
            "comments": 0
          },
          {
            "ep": 39,
            "comments": 0
          },
          {
            "ep": 40,
            "comments": 0
          },
          {
            "ep": 41,
            "comments": 0
          },
          {
            "ep": 42,
            "comments": 0
          },
          {
            "ep": 43,
            "comments": 0
          },
          {
            "ep": 44,
            "comments": 0
          },
          {
            "ep": 45,
            "comments": 0
          },
          {
            "ep": 46,
            "comments": 0
          },
          {
            "ep": 47,
            "comments": 0
          },
          {
            "ep": 48,
            "comments": 0
          },
          {
            "ep": 49,
            "comments": 0
          },
          {
            "ep": 50,
            "comments": 0
          },
          {
            "ep": 51,
            "comments": 0
          },
          {
            "ep": 52,
            "comments": 0
          }
        ]
      }
    },
    {
      "images": {
        "grid": "https://lain.bgm.tv/r/100/pic/cover/l/bd/2f/255980_QS121.jpg",
        "common": "https://lain.bgm.tv/r/400/pic/cover/l/bd/2f/255980_QS121.jpg"
      },
      "name": "MIX MEISEI STORY",
      "name_cn": "MIX：明青故事",
      "infobox": [
        {
          "key": "放送星期",
          "value": "星期六"
        }
      ],
      "rating": {
        "rank": 1098,
        "total": 821,
        "count": {
          "1": 4,
          "2": 0,
          "3": 1,
          "4": 6,
          "5": 26,
          "6": 80,
          "7": 279,
          "8": 342,
          "9": 64,
          "10": 19
        },
        "score": 7.4
      },
      "total_episodes": 24,
      "collection": {
        "on_hold": 130,
        "dropped": 77,
        "wish": 538,
        "collect": 1128,
        "doing": 216
      },
      "id": 255980,
      "meta_tags": [
        "TV",
        "恋爱",
        "日本",
        "运动",
        "漫画改"
      ],
      "nsfw": false,
      "episodes_summary": {
        "aired_episodes": 24,
        "total_comments": 391,
        "episodes": [
          {
            "ep": 1,
            "comments": 26
          },
          {
            "ep": 2,
            "comments": 20
          },
          {
            "ep": 3,
            "comments": 15
          },
          {
            "ep": 4,
            "comments": 16
          },
          {
            "ep": 5,
            "comments": 15
          },
          {
            "ep": 6,
            "comments": 26
          },
          {
            "ep": 7,
            "comments": 20
          },
          {
            "ep": 8,
            "comments": 18
          },
          {
            "ep": 9,
            "comments": 18
          },
          {
            "ep": 10,
            "comments": 31
          },
          {
            "ep": 11,
            "comments": 11
          },
          {
            "ep": 12,
            "comments": 11
          },
          {
            "ep": 13,
            "comments": 15
          },
          {
            "ep": 14,
            "comments": 20
          },
          {
            "ep": 15,
            "comments": 15
          },
          {
            "ep": 16,
            "comments": 13
          },
          {
            "ep": 17,
            "comments": 17
          },
          {
            "ep": 18,
            "comments": 14
          },
          {
            "ep": 19,
            "comments": 8
          },
          {
            "ep": 20,
            "comments": 9
          },
          {
            "ep": 21,
            "comments": 10
          },
          {
            "ep": 22,
            "comments": 10
          },
          {
            "ep": 23,
            "comments": 17
          },
          {
            "ep": 24,
            "comments": 16
          }
        ]
      }
    },
    {
      "images": {
        "grid": "https://lain.bgm.tv/r/100/pic/cover/l/b9/55/260373_2Z2oz.jpg",
        "common": "https://lain.bgm.tv/r/400/pic/cover/l/b9/55/260373_2Z2oz.jpg"
      },
      "name": "超可動ガール1/6",
      "name_cn": "超可动女孩1/6",
      "infobox": [
        {
          "key": "放送星期",
          "value": "星期六"
        }
      ],
      "rating": {
        "rank": 4344,
        "total": 350,
        "count": {
          "1": 1,
          "2": 2,
          "3": 0,
          "4": 11,
          "5": 32,
          "6": 101,
          "7": 148,
          "8": 47,
          "9": 5,
          "10": 3
        },
        "score": 6.6
      },
      "total_episodes": 12,
      "collection": {
        "on_hold": 48,
        "dropped": 51,
        "wish": 199,
        "collect": 521,
        "doing": 46
      },
      "id": 260373,
      "meta_tags": [
        "后宫",
        "TV",
        "日本",
        "漫画改"
      ],
      "nsfw": false,
      "episodes_summary": {
        "aired_episodes": 12,
        "total_comments": 137,
        "episodes": [
          {
            "ep": 1,
            "comments": 11
          },
          {
            "ep": 2,
            "comments": 17
          },
          {
            "ep": 3,
            "comments": 13
          },
          {
            "ep": 4,
            "comments": 8
          },
          {
            "ep": 5,
            "comments": 7
          },
          {
            "ep": 6,
            "comments": 11
          },
          {
            "ep": 7,
            "comments": 15
          },
          {
            "ep": 8,
            "comments": 14
          },
          {
            "ep": 9,
            "comments": 11
          },
          {
            "ep": 10,
            "comments": 7
          },
          {
            "ep": 11,
            "comments": 11
          },
          {
            "ep": 12,
            "comments": 12
          }
        ]
      }
    },
    {
      "images": {
        "grid": "https://lain.bgm.tv/r/100/pic/cover/l/81/26/260371_E1a69.jpg",
        "common": "https://lain.bgm.tv/r/400/pic/cover/l/81/26/260371_E1a69.jpg"
      },
      "name": "女子かう生",
      "name_cn": "女子高中生",
      "infobox": [
        {
          "key": "放送星期",
          "value": "星期六"
        }
      ],
      "rating": {
        "rank": 7448,
        "total": 644,
        "count": {
          "1": 6,
          "2": 2,
          "3": 10,
          "4": 41,
          "5": 134,
          "6": 286,
          "7": 124,
          "8": 30,
          "9": 4,
          "10": 7
        },
        "score": 5.9
      },
      "total_episodes": 12,
      "collection": {
        "on_hold": 88,
        "dropped": 114,
        "wish": 448,
        "collect": 1116,
        "doing": 97
      },
      "id": 260371,
      "meta_tags": [
        "百合",
        "TV",
        "日本",
        "漫画改",
        "日常"
      ],
      "nsfw": false,
      "episodes_summary": {
        "aired_episodes": 12,
        "total_comments": 154,
        "episodes": [
          {
            "ep": 1,
            "comments": 33
          },
          {
            "ep": 2,
            "comments": 11
          },
          {
            "ep": 3,
            "comments": 10
          },
          {
            "ep": 4,
            "comments": 12
          },
          {
            "ep": 5,
            "comments": 11
          },
          {
            "ep": 6,
            "comments": 8
          },
          {
            "ep": 7,
            "comments": 11
          },
          {
            "ep": 8,
            "comments": 15
          },
          {
            "ep": 9,
            "comments": 7
          },
          {
            "ep": 10,
            "comments": 14
          },
          {
            "ep": 11,
            "comments": 5
          },
          {
            "ep": 12,
            "comments": 17
          }
        ]
      }
    },
    {
      "images": {
        "grid": "https://lain.bgm.tv/r/100/pic/cover/l/3e/19/269075_5g48K.jpg",
        "common": "https://lain.bgm.tv/r/400/pic/cover/l/3e/19/269075_5g48K.jpg"
      },
      "name": "ノブナガ先生の幼な妻",
      "name_cn": "信长老师的年幼妻子",
      "infobox": [
        {
          "key": "放送星期",
          "value": "星期六"
        }
      ],
      "rating": {
        "rank": 8465,
        "total": 830,
        "count": {
          "1": 7,
          "2": 10,
          "3": 29,
          "4": 97,
          "5": 254,
          "6": 310,
          "7": 88,
          "8": 13,
          "9": 8,
          "10": 14
        },
        "score": 5.5
      },
      "total_episodes": 12,
      "collection": {
        "on_hold": 113,
        "dropped": 161,
        "wish": 355,
        "collect": 1398,
        "doing": 108
      },
      "id": 269075,
      "meta_tags": [
        "后宫",
        "TV",
        "日本",
        "漫画改"
      ],
      "nsfw": false,
      "episodes_summary": {
        "aired_episodes": 12,
        "total_comments": 156,
        "episodes": [
          {
            "ep": 1,
            "comments": 22
          },
          {
            "ep": 2,
            "comments": 14
          },
          {
            "ep": 3,
            "comments": 14
          },
          {
            "ep": 4,
            "comments": 15
          },
          {
            "ep": 5,
            "comments": 9
          },
          {
            "ep": 6,
            "comments": 9
          },
          {
            "ep": 7,
            "comments": 8
          },
          {
            "ep": 8,
            "comments": 14
          },
          {
            "ep": 9,
            "comments": 5
          },
          {
            "ep": 10,
            "comments": 19
          },
          {
            "ep": 11,
            "comments": 10
          },
          {
            "ep": 12,
            "comments": 17
          }
        ]
      }
    },
    {
      "images": {
        "grid": "https://lain.bgm.tv/r/100/pic/cover/l/9d/d1/245665_5an54.jpg",
        "common": "https://lain.bgm.tv/r/400/pic/cover/l/9d/d1/245665_5an54.jpg"
      },
      "name": "鬼滅の刃",
      "name_cn": "鬼灭之刃",
      "infobox": [
        {
          "key": "放送星期",
          "value": "星期六"
        }
      ],
      "rating": {
        "rank": 1485,
        "total": 17216,
        "count": {
          "1": 58,
          "2": 30,
          "3": 53,
          "4": 148,
          "5": 563,
          "6": 2302,
          "7": 6915,
          "8": 5543,
          "9": 1020,
          "10": 584
        },
        "score": 7.3
      },
      "total_episodes": 26,
      "collection": {
        "on_hold": 715,
        "dropped": 740,
        "wish": 1200,
        "collect": 27678,
        "doing": 1260
      },
      "id": 245665,
      "meta_tags": [
        "TV",
        "日本",
        "漫画改",
        "战斗"
      ],
      "nsfw": false,
      "episodes_summary": {
        "aired_episodes": 26,
        "total_comments": 2061,
        "episodes": [
          {
            "ep": 1,
            "comments": 146
          },
          {
            "ep": 2,
            "comments": 94
          },
          {
            "ep": 3,
            "comments": 98
          },
          {
            "ep": 4,
            "comments": 106
          },
          {
            "ep": 5,
            "comments": 53
          },
          {
            "ep": 6,
            "comments": 76
          },
          {
            "ep": 7,
            "comments": 81
          },
          {
            "ep": 8,
            "comments": 69
          },
          {
            "ep": 9,
            "comments": 95
          },
          {
            "ep": 10,
            "comments": 76
          },
          {
            "ep": 11,
            "comments": 68
          },
          {
            "ep": 12,
            "comments": 58
          },
          {
            "ep": 13,
            "comments": 92
          },
          {
            "ep": 14,
            "comments": 82
          },
          {
            "ep": 15,
            "comments": 41
          },
          {
            "ep": 16,
            "comments": 53
          },
          {
            "ep": 17,
            "comments": 78
          },
          {
            "ep": 18,
            "comments": 67
          },
          {
            "ep": 19,
            "comments": 195
          },
          {
            "ep": 20,
            "comments": 68
          },
          {
            "ep": 21,
            "comments": 70
          },
          {
            "ep": 22,
            "comments": 90
          },
          {
            "ep": 23,
            "comments": 49
          },
          {
            "ep": 24,
            "comments": 40
          },
          {
            "ep": 25,
            "comments": 44
          },
          {
            "ep": 26,
            "comments": 72
          }
        ]
      }
    },
    {
      "images": {
        "grid": "https://lain.bgm.tv/r/100/pic/cover/l/21/a6/257369_32HM0.jpg",
        "common": "https://lain.bgm.tv/r/400/pic/cover/l/21/a6/257369_32HM0.jpg"
      },
      "name": "ぼくたちは勉強ができない",
      "name_cn": "我们真的学不来",
      "infobox": [
        {
          "key": "放送星期",
          "value": "星期六"
        }
      ],
      "rating": {
        "rank": 6338,
        "total": 4248,
        "count": {
          "1": 17,
          "2": 19,
          "3": 44,
          "4": 147,
          "5": 580,
          "6": 1676,
          "7": 1370,
          "8": 307,
          "9": 44,
          "10": 44
        },
        "score": 6.3
      },
      "total_episodes": 13,
      "collection": {
        "on_hold": 354,
        "dropped": 510,
        "wish": 919,
        "collect": 7121,
        "doing": 414
      },
      "id": 257369,
      "meta_tags": [
        "后宫",
        "TV",
        "恋爱",
        "日本",
        "漫画改"
      ],
      "nsfw": false,
      "episodes_summary": {
        "aired_episodes": 13,
        "total_comments": 520,
        "episodes": [
          {
            "ep": 1,
            "comments": 79
          },
          {
            "ep": 2,
            "comments": 36
          },
          {
            "ep": 3,
            "comments": 24
          },
          {
            "ep": 4,
            "comments": 36
          },
          {
            "ep": 5,
            "comments": 35
          },
          {
            "ep": 6,
            "comments": 31
          },
          {
            "ep": 7,
            "comments": 33
          },
          {
            "ep": 8,
            "comments": 36
          },
          {
            "ep": 9,
            "comments": 56
          },
          {
            "ep": 10,
            "comments": 36
          },
          {
            "ep": 11,
            "comments": 40
          },
          {
            "ep": 12,
            "comments": 39
          },
          {
            "ep": 13,
            "comments": 39
          }
        ]
      }
    },
    {
      "images": {
        "grid": "https://lain.bgm.tv/r/100/pic/cover/l/17/7f/254788_5501o.jpg",
        "common": "https://lain.bgm.tv/r/400/pic/cover/l/17/7f/254788_5501o.jpg"
      },
      "name": "この音とまれ！",
      "name_cn": "一弦定音！",
      "infobox": [
        {
          "key": "放送星期",
          "value": "星期六"
        }
      ],
      "rating": {
        "rank": 5549,
        "total": 447,
        "count": {
          "1": 3,
          "2": 1,
          "3": 2,
          "4": 22,
          "5": 66,
          "6": 147,
          "7": 142,
          "8": 50,
          "9": 5,
          "10": 9
        },
        "score": 6.4
      },
      "total_episodes": 13,
      "collection": {
        "on_hold": 101,
        "dropped": 136,
        "wish": 332,
        "collect": 674,
        "doing": 93
      },
      "id": 254788,
      "meta_tags": [
        "校园",
        "TV",
        "日本",
        "漫画改",
        "音乐"
      ],
      "nsfw": false,
      "episodes_summary": {
        "aired_episodes": 13,
        "total_comments": 214,
        "episodes": [
          {
            "ep": 1,
            "comments": 41
          },
          {
            "ep": 2,
            "comments": 21
          },
          {
            "ep": 3,
            "comments": 16
          },
          {
            "ep": 4,
            "comments": 9
          },
          {
            "ep": 5,
            "comments": 21
          },
          {
            "ep": 6,
            "comments": 19
          },
          {
            "ep": 7,
            "comments": 18
          },
          {
            "ep": 8,
            "comments": 12
          },
          {
            "ep": 9,
            "comments": 16
          },
          {
            "ep": 10,
            "comments": 9
          },
          {
            "ep": 11,
            "comments": 11
          },
          {
            "ep": 12,
            "comments": 9
          },
          {
            "ep": 13,
            "comments": 12
          }
        ]
      }
    },
    {
      "images": {
        "grid": "https://lain.bgm.tv/r/100/pic/cover/l/5a/df/269023_0a1L6.jpg",
        "common": "https://lain.bgm.tv/r/400/pic/cover/l/5a/df/269023_0a1L6.jpg"
      },
      "name": "キラッとプリ☆チャン シーズン2",
      "name_cn": "闪亮美妙☆频道 第二季",
      "infobox": [
        {
          "key": "放送星期",
          "value": "星期日"
        }
      ],
      "rating": {
        "rank": 1910,
        "total": 70,
        "count": {
          "1": 0,
          "2": 0,
          "3": 0,
          "4": 2,
          "5": 1,
          "6": 16,
          "7": 27,
          "8": 15,
          "9": 3,
          "10": 6
        },
        "score": 7.2
      },
      "total_episodes": 51,
      "collection": {
        "on_hold": 6,
        "dropped": 19,
        "wish": 53,
        "collect": 99,
        "doing": 15
      },
      "id": 269023,
      "meta_tags": [
        "TV",
        "日本",
        "原创"
      ],
      "nsfw": false,
      "episodes_summary": {
        "aired_episodes": 51,
        "total_comments": 297,
        "episodes": [
          {
            "ep": 1,
            "comments": 9
          },
          {
            "ep": 2,
            "comments": 11
          },
          {
            "ep": 3,
            "comments": 4
          },
          {
            "ep": 4,
            "comments": 5
          },
          {
            "ep": 5,
            "comments": 4
          },
          {
            "ep": 6,
            "comments": 5
          },
          {
            "ep": 7,
            "comments": 2
          },
          {
            "ep": 8,
            "comments": 2
          },
          {
            "ep": 9,
            "comments": 8
          },
          {
            "ep": 10,
            "comments": 6
          },
          {
            "ep": 11,
            "comments": 5
          },
          {
            "ep": 12,
            "comments": 9
          },
          {
            "ep": 13,
            "comments": 9
          },
          {
            "ep": 14,
            "comments": 7
          },
          {
            "ep": 15,
            "comments": 3
          },
          {
            "ep": 16,
            "comments": 3
          },
          {
            "ep": 17,
            "comments": 6
          },
          {
            "ep": 18,
            "comments": 7
          },
          {
            "ep": 19,
            "comments": 4
          },
          {
            "ep": 20,
            "comments": 5
          },
          {
            "ep": 21,
            "comments": 7
          },
          {
            "ep": 22,
            "comments": 5
          },
          {
            "ep": 23,
            "comments": 3
          },
          {
            "ep": 24,
            "comments": 6
          },
          {
            "ep": 25,
            "comments": 5
          },
          {
            "ep": 26,
            "comments": 5
          },
          {
            "ep": 27,
            "comments": 10
          },
          {
            "ep": 28,
            "comments": 6
          },
          {
            "ep": 29,
            "comments": 4
          },
          {
            "ep": 30,
            "comments": 7
          },
          {
            "ep": 31,
            "comments": 3
          },
          {
            "ep": 32,
            "comments": 5
          },
          {
            "ep": 33,
            "comments": 6
          },
          {
            "ep": 34,
            "comments": 9
          },
          {
            "ep": 35,
            "comments": 7
          },
          {
            "ep": 36,
            "comments": 5
          },
          {
            "ep": 37,
            "comments": 11
          },
          {
            "ep": 38,
            "comments": 5
          },
          {
            "ep": 39,
            "comments": 6
          },
          {
            "ep": 40,
            "comments": 6
          },
          {
            "ep": 41,
            "comments": 6
          },
          {
            "ep": 42,
            "comments": 5
          },
          {
            "ep": 43,
            "comments": 6
          },
          {
            "ep": 44,
            "comments": 4
          },
          {
            "ep": 45,
            "comments": 5
          },
          {
            "ep": 46,
            "comments": 4
          },
          {
            "ep": 47,
            "comments": 3
          },
          {
            "ep": 48,
            "comments": 6
          },
          {
            "ep": 49,
            "comments": 9
          },
          {
            "ep": 50,
            "comments": 8
          },
          {
            "ep": 51,
            "comments": 6
          }
        ]
      }
    },
    {
      "images": {
        "grid": "https://lain.bgm.tv/r/100/pic/cover/l/3a/46/247886_2HP7z.jpg",
        "common": "https://lain.bgm.tv/r/400/pic/cover/l/3a/46/247886_2HP7z.jpg"
      },
      "name": "消滅都市",
      "name_cn": "消灭都市",
      "infobox": [
        {
          "key": "放送星期",
          "value": "星期日"
        }
      ],
      "rating": {
        "rank": 8940,
        "total": 349,
        "count": {
          "1": 8,
          "2": 11,
          "3": 23,
          "4": 67,
          "5": 131,
          "6": 79,
          "7": 20,
          "8": 8,
          "9": 1,
          "10": 1
        },
        "score": 4.9
      },
      "total_episodes": 12,
      "collection": {
        "on_hold": 106,
        "dropped": 268,
        "wish": 182,
        "collect": 463,
        "doing": 90
      },
      "id": 247886,
      "meta_tags": [
        "TV",
        "日本",
        "游戏改"
      ],
      "nsfw": false,
      "episodes_summary": {
        "aired_episodes": 12,
        "total_comments": 105,
        "episodes": [
          {
            "ep": 1,
            "comments": 27
          },
          {
            "ep": 2,
            "comments": 9
          },
          {
            "ep": 3,
            "comments": 11
          },
          {
            "ep": 4,
            "comments": 8
          },
          {
            "ep": 5,
            "comments": 6
          },
          {
            "ep": 6,
            "comments": 7
          },
          {
            "ep": 7,
            "comments": 6
          },
          {
            "ep": 8,
            "comments": 5
          },
          {
            "ep": 9,
            "comments": 8
          },
          {
            "ep": 10,
            "comments": 4
          },
          {
            "ep": 11,
            "comments": 5
          },
          {
            "ep": 12,
            "comments": 9
          }
        ]
      }
    },
    {
      "images": {
        "grid": "https://lain.bgm.tv/r/100/pic/cover/l/08/e2/275610_zIO8s.jpg",
        "common": "https://lain.bgm.tv/r/400/pic/cover/l/08/e2/275610_zIO8s.jpg"
      },
      "name": "洗い屋さん！～俺とアイツが女湯で!?～",
      "name_cn": "洗浴服务！～我和那家伙在女浴池！？～",
      "infobox": [
        {
          "key": "放送星期",
          "value": "星期日"
        }
      ],
      "rating": {
        "rank": 6755,
        "total": 764,
        "count": {
          "1": 1,
          "2": 12,
          "3": 9,
          "4": 29,
          "5": 149,
          "6": 310,
          "7": 162,
          "8": 71,
          "9": 9,
          "10": 12
        },
        "score": 6.1
      },
      "total_episodes": 8,
      "collection": {
        "on_hold": 79,
        "dropped": 82,
        "wish": 301,
        "collect": 1396,
        "doing": 83
      },
      "id": 275610,
      "meta_tags": [
        "TV",
        "日本",
        "漫画改"
      ],
      "nsfw": true,
      "episodes_summary": {
        "aired_episodes": 8,
        "total_comments": 95,
        "episodes": [
          {
            "ep": 1,
            "comments": 15
          },
          {
            "ep": 2,
            "comments": 14
          },
          {
            "ep": 3,
            "comments": 8
          },
          {
            "ep": 4,
            "comments": 20
          },
          {
            "ep": 5,
            "comments": 12
          },
          {
            "ep": 6,
            "comments": 11
          },
          {
            "ep": 7,
            "comments": 5
          },
          {
            "ep": 8,
            "comments": 10
          }
        ]
      }
    },
    {
      "images": {
        "grid": "https://lain.bgm.tv/r/100/pic/cover/l/39/23/272475_k60P6.jpg",
        "common": "https://lain.bgm.tv/r/400/pic/cover/l/39/23/272475_k60P6.jpg"
      },
      "name": "Fairy gone フェアリーゴーン",
      "name_cn": "Fairy gone",
      "infobox": [
        {
          "key": "放送星期",
          "value": "星期日"
        }
      ],
      "rating": {
        "rank": 8577,
        "total": 465,
        "count": {
          "1": 10,
          "2": 7,
          "3": 26,
          "4": 67,
          "5": 114,
          "6": 168,
          "7": 56,
          "8": 11,
          "9": 1,
          "10": 5
        },
        "score": 5.3
      },
      "total_episodes": 12,
      "collection": {
        "on_hold": 134,
        "dropped": 319,
        "wish": 279,
        "collect": 573,
        "doing": 120
      },
      "id": 272475,
      "meta_tags": [
        "TV",
        "日本",
        "奇幻",
        "原创",
        "战斗"
      ],
      "nsfw": false,
      "episodes_summary": {
        "aired_episodes": 12,
        "total_comments": 295,
        "episodes": [
          {
            "ep": 1,
            "comments": 70
          },
          {
            "ep": 2,
            "comments": 39
          },
          {
            "ep": 3,
            "comments": 25
          },
          {
            "ep": 4,
            "comments": 16
          },
          {
            "ep": 5,
            "comments": 13
          },
          {
            "ep": 6,
            "comments": 17
          },
          {
            "ep": 7,
            "comments": 10
          },
          {
            "ep": 8,
            "comments": 14
          },
          {
            "ep": 9,
            "comments": 28
          },
          {
            "ep": 10,
            "comments": 19
          },
          {
            "ep": 11,
            "comments": 21
          },
          {
            "ep": 12,
            "comments": 23
          }
        ]
      }
    },
    {
      "images": {
        "grid": "https://lain.bgm.tv/r/100/pic/cover/l/8e/68/250724_053c1.jpg",
        "common": "https://lain.bgm.tv/r/400/pic/cover/l/8e/68/250724_053c1.jpg"
      },
      "name": "真夜中のオカルト公務員",
      "name_cn": "深夜的超自然公务员",
      "infobox": [
        {
          "key": "放送星期",
          "value": "星期日"
        }
      ],
      "rating": {
        "rank": 8500,
        "total": 420,
        "count": {
          "1": 2,
          "2": 5,
          "3": 16,
          "4": 56,
          "5": 147,
          "6": 135,
          "7": 45,
          "8": 10,
          "9": 1,
          "10": 3
        },
        "score": 5.4
      },
      "total_episodes": 12,
      "collection": {
        "on_hold": 113,
        "dropped": 280,
        "wish": 179,
        "collect": 601,
        "doing": 93
      },
      "id": 250724,
      "meta_tags": [
        "TV",
        "日本",
        "奇幻",
        "漫画改"
      ],
      "nsfw": false,
      "episodes_summary": {
        "aired_episodes": 12,
        "total_comments": 91,
        "episodes": [
          {
            "ep": 1,
            "comments": 26
          },
          {
            "ep": 2,
            "comments": 11
          },
          {
            "ep": 3,
            "comments": 13
          },
          {
            "ep": 4,
            "comments": 5
          },
          {
            "ep": 5,
            "comments": 4
          },
          {
            "ep": 6,
            "comments": 3
          },
          {
            "ep": 7,
            "comments": 3
          },
          {
            "ep": 8,
            "comments": 6
          },
          {
            "ep": 9,
            "comments": 6
          },
          {
            "ep": 10,
            "comments": 5
          },
          {
            "ep": 11,
            "comments": 4
          },
          {
            "ep": 12,
            "comments": 5
          }
        ]
      }
    },
    {
      "images": {
        "grid": "https://lain.bgm.tv/r/100/pic/cover/l/ef/65/262111_Qczq5.jpg",
        "common": "https://lain.bgm.tv/r/400/pic/cover/l/ef/65/262111_Qczq5.jpg"
      },
      "name": "なんでここに先生が!?",
      "name_cn": "为什么老师会在这里！？",
      "infobox": [
        {
          "key": "放送星期",
          "value": "星期日"
        }
      ],
      "rating": {
        "rank": 6828,
        "total": 2570,
        "count": {
          "1": 10,
          "2": 9,
          "3": 32,
          "4": 108,
          "5": 452,
          "6": 1085,
          "7": 629,
          "8": 177,
          "9": 32,
          "10": 36
        },
        "score": 6.1
      },
      "total_episodes": 13,
      "collection": {
        "on_hold": 272,
        "dropped": 284,
        "wish": 927,
        "collect": 4462,
        "doing": 321
      },
      "id": 262111,
      "meta_tags": [
        "校园",
        "TV",
        "恋爱",
        "日本",
        "漫画改"
      ],
      "nsfw": false,
      "episodes_summary": {
        "aired_episodes": 12,
        "total_comments": 263,
        "episodes": [
          {
            "ep": 1,
            "comments": 39
          },
          {
            "ep": 2,
            "comments": 26
          },
          {
            "ep": 3,
            "comments": 26
          },
          {
            "ep": 4,
            "comments": 18
          },
          {
            "ep": 5,
            "comments": 32
          },
          {
            "ep": 6,
            "comments": 26
          },
          {
            "ep": 7,
            "comments": 20
          },
          {
            "ep": 8,
            "comments": 20
          },
          {
            "ep": 9,
            "comments": 12
          },
          {
            "ep": 10,
            "comments": 17
          },
          {
            "ep": 11,
            "comments": 13
          },
          {
            "ep": 12,
            "comments": 14
          }
        ]
      }
    },
    {
      "images": {
        "grid": "https://lain.bgm.tv/r/100/pic/cover/l/15/ac/255667_8xJxj.jpg",
        "common": "https://lain.bgm.tv/r/400/pic/cover/l/15/ac/255667_8xJxj.jpg"
      },
      "name": "八月のシンデレラナイン",
      "name_cn": "八月的灰姑娘棒球队",
      "infobox": [
        {
          "key": "放送星期",
          "value": "星期日"
        }
      ],
      "rating": {
        "rank": 7653,
        "total": 410,
        "count": {
          "1": 3,
          "2": 3,
          "3": 10,
          "4": 34,
          "5": 106,
          "6": 152,
          "7": 72,
          "8": 24,
          "9": 4,
          "10": 2
        },
        "score": 5.8
      },
      "total_episodes": 13,
      "collection": {
        "on_hold": 111,
        "dropped": 197,
        "wish": 251,
        "collect": 612,
        "doing": 164
      },
      "id": 255667,
      "meta_tags": [
        "百合",
        "TV",
        "日本",
        "游戏改"
      ],
      "nsfw": false,
      "episodes_summary": {
        "aired_episodes": 12,
        "total_comments": 145,
        "episodes": [
          {
            "ep": 1,
            "comments": 27
          },
          {
            "ep": 2,
            "comments": 20
          },
          {
            "ep": 3,
            "comments": 12
          },
          {
            "ep": 4,
            "comments": 12
          },
          {
            "ep": 5,
            "comments": 9
          },
          {
            "ep": 6,
            "comments": 12
          },
          {
            "ep": 7,
            "comments": 10
          },
          {
            "ep": 8,
            "comments": 15
          },
          {
            "ep": 9,
            "comments": 7
          },
          {
            "ep": 10,
            "comments": 7
          },
          {
            "ep": 11,
            "comments": 7
          },
          {
            "ep": 12,
            "comments": 7
          }
        ]
      }
    },
    {
      "images": {
        "grid": "https://lain.bgm.tv/r/100/pic/cover/l/f7/d7/256561_2I1Pp.jpg",
        "common": "https://lain.bgm.tv/r/400/pic/cover/l/f7/d7/256561_2I1Pp.jpg"
      },
      "name": "なむあみだ仏っ！-蓮台 UTENA-",
      "name_cn": "南无阿弥陀佛！-莲台 UTENA-",
      "infobox": [
        {
          "key": "放送星期",
          "value": "星期一"
        }
      ],
      "rating": {
        "rank": 0,
        "total": 34,
        "count": {
          "1": 1,
          "2": 2,
          "3": 4,
          "4": 4,
          "5": 10,
          "6": 6,
          "7": 5,
          "8": 2,
          "9": 0,
          "10": 0
        },
        "score": 5
      },
      "total_episodes": 12,
      "collection": {
        "on_hold": 10,
        "dropped": 46,
        "wish": 32,
        "collect": 45,
        "doing": 10
      },
      "id": 256561,
      "meta_tags": [
        "TV",
        "日本",
        "游戏改"
      ],
      "nsfw": false,
      "episodes_summary": {
        "aired_episodes": 12,
        "total_comments": 18,
        "episodes": [
          {
            "ep": 1,
            "comments": 1
          },
          {
            "ep": 2,
            "comments": 3
          },
          {
            "ep": 3,
            "comments": 1
          },
          {
            "ep": 4,
            "comments": 0
          },
          {
            "ep": 5,
            "comments": 1
          },
          {
            "ep": 6,
            "comments": 2
          },
          {
            "ep": 7,
            "comments": 4
          },
          {
            "ep": 8,
            "comments": 1
          },
          {
            "ep": 9,
            "comments": 1
          },
          {
            "ep": 10,
            "comments": 1
          },
          {
            "ep": 11,
            "comments": 1
          },
          {
            "ep": 12,
            "comments": 2
          }
        ]
      }
    },
    {
      "images": {
        "grid": "https://lain.bgm.tv/r/100/pic/cover/l/f2/be/267250_cMvqQ.jpg",
        "common": "https://lain.bgm.tv/r/400/pic/cover/l/f2/be/267250_cMvqQ.jpg"
      },
      "name": "RobiHachi",
      "name_cn": "",
      "infobox": [
        {
          "key": "放送星期",
          "value": "星期一"
        }
      ],
      "rating": {
        "rank": 6266,
        "total": 504,
        "count": {
          "1": 2,
          "2": 1,
          "3": 4,
          "4": 19,
          "5": 80,
          "6": 199,
          "7": 157,
          "8": 34,
          "9": 6,
          "10": 2
        },
        "score": 6.2
      },
      "total_episodes": 12,
      "collection": {
        "on_hold": 101,
        "dropped": 185,
        "wish": 200,
        "collect": 713,
        "doing": 84
      },
      "id": 267250,
      "meta_tags": [
        "科幻",
        "TV",
        "日本",
        "原创"
      ],
      "nsfw": false,
      "episodes_summary": {
        "aired_episodes": 12,
        "total_comments": 167,
        "episodes": [
          {
            "ep": 1,
            "comments": 34
          },
          {
            "ep": 2,
            "comments": 24
          },
          {
            "ep": 3,
            "comments": 21
          },
          {
            "ep": 4,
            "comments": 7
          },
          {
            "ep": 5,
            "comments": 6
          },
          {
            "ep": 6,
            "comments": 14
          },
          {
            "ep": 7,
            "comments": 11
          },
          {
            "ep": 8,
            "comments": 11
          },
          {
            "ep": 9,
            "comments": 12
          },
          {
            "ep": 10,
            "comments": 12
          },
          {
            "ep": 11,
            "comments": 6
          },
          {
            "ep": 12,
            "comments": 9
          }
        ]
      }
    },
    {
      "images": {
        "grid": "https://lain.bgm.tv/r/100/pic/cover/l/06/53/249245_wBXfw.jpg",
        "common": "https://lain.bgm.tv/r/400/pic/cover/l/06/53/249245_wBXfw.jpg"
      },
      "name": "KING OF PRISM -Shiny Seven Stars-",
      "name_cn": "绫镜少男 KING OF PRISM -Shiny Seven Stars",
      "infobox": [
        {
          "key": "放送星期",
          "value": "星期一"
        }
      ],
      "rating": {
        "rank": 2750,
        "total": 52,
        "count": {
          "1": 0,
          "2": 1,
          "3": 0,
          "4": 1,
          "5": 7,
          "6": 13,
          "7": 14,
          "8": 11,
          "9": 0,
          "10": 5
        },
        "score": 6.8
      },
      "total_episodes": 13,
      "collection": {
        "on_hold": 15,
        "dropped": 29,
        "wish": 39,
        "collect": 76,
        "doing": 15
      },
      "id": 249245,
      "meta_tags": [
        "TV",
        "日本",
        "原创"
      ],
      "nsfw": false,
      "episodes_summary": {
        "aired_episodes": 12,
        "total_comments": 150,
        "episodes": [
          {
            "ep": 1,
            "comments": 15
          },
          {
            "ep": 2,
            "comments": 7
          },
          {
            "ep": 3,
            "comments": 15
          },
          {
            "ep": 4,
            "comments": 14
          },
          {
            "ep": 5,
            "comments": 11
          },
          {
            "ep": 6,
            "comments": 8
          },
          {
            "ep": 7,
            "comments": 18
          },
          {
            "ep": 8,
            "comments": 13
          },
          {
            "ep": 9,
            "comments": 13
          },
          {
            "ep": 10,
            "comments": 13
          },
          {
            "ep": 11,
            "comments": 10
          },
          {
            "ep": 12,
            "comments": 13
          }
        ]
      }
    },
    {
      "images": {
        "grid": "https://lain.bgm.tv/r/100/pic/cover/l/c0/e9/262865_P6q49.jpg",
        "common": "https://lain.bgm.tv/r/400/pic/cover/l/c0/e9/262865_P6q49.jpg"
      },
      "name": "異世界かるてっと",
      "name_cn": "异世界四重奏",
      "infobox": [
        {
          "key": "放送星期",
          "value": "星期二"
        }
      ],
      "rating": {
        "rank": 4165,
        "total": 3090,
        "count": {
          "1": 2,
          "2": 4,
          "3": 3,
          "4": 38,
          "5": 239,
          "6": 932,
          "7": 1446,
          "8": 355,
          "9": 38,
          "10": 33
        },
        "score": 6.7
      },
      "total_episodes": 12,
      "collection": {
        "on_hold": 287,
        "dropped": 228,
        "wish": 562,
        "collect": 5366,
        "doing": 332
      },
      "id": 262865,
      "meta_tags": [
        "TV",
        "日本",
        "原创",
        "穿越"
      ],
      "nsfw": false,
      "episodes_summary": {
        "aired_episodes": 12,
        "total_comments": 350,
        "episodes": [
          {
            "ep": 1,
            "comments": 39
          },
          {
            "ep": 2,
            "comments": 38
          },
          {
            "ep": 3,
            "comments": 29
          },
          {
            "ep": 4,
            "comments": 28
          },
          {
            "ep": 5,
            "comments": 39
          },
          {
            "ep": 6,
            "comments": 24
          },
          {
            "ep": 7,
            "comments": 19
          },
          {
            "ep": 8,
            "comments": 29
          },
          {
            "ep": 9,
            "comments": 27
          },
          {
            "ep": 10,
            "comments": 29
          },
          {
            "ep": 11,
            "comments": 20
          },
          {
            "ep": 12,
            "comments": 29
          }
        ]
      }
    },
    {
      "images": {
        "grid": "https://lain.bgm.tv/r/100/pic/cover/l/71/f6/253048_38KLC.jpg",
        "common": "https://lain.bgm.tv/r/400/pic/cover/l/71/f6/253048_38KLC.jpg"
      },
      "name": "ストライクウィッチーズ 501部隊発進しますっ！",
      "name_cn": "强袭魔女 501部队起飞！",
      "infobox": [
        {
          "key": "放送星期",
          "value": "星期二"
        }
      ],
      "rating": {
        "rank": 4915,
        "total": 477,
        "count": {
          "1": 5,
          "2": 2,
          "3": 4,
          "4": 12,
          "5": 57,
          "6": 141,
          "7": 175,
          "8": 65,
          "9": 8,
          "10": 8
        },
        "score": 6.5
      },
      "total_episodes": 12,
      "collection": {
        "on_hold": 51,
        "dropped": 78,
        "wish": 330,
        "collect": 817,
        "doing": 50
      },
      "id": 253048,
      "meta_tags": [
        "百合",
        "TV",
        "日本",
        "漫画改"
      ],
      "nsfw": false,
      "episodes_summary": {
        "aired_episodes": 12,
        "total_comments": 129,
        "episodes": [
          {
            "ep": 1,
            "comments": 20
          },
          {
            "ep": 2,
            "comments": 11
          },
          {
            "ep": 3,
            "comments": 14
          },
          {
            "ep": 4,
            "comments": 9
          },
          {
            "ep": 5,
            "comments": 7
          },
          {
            "ep": 6,
            "comments": 5
          },
          {
            "ep": 7,
            "comments": 10
          },
          {
            "ep": 8,
            "comments": 12
          },
          {
            "ep": 9,
            "comments": 5
          },
          {
            "ep": 10,
            "comments": 7
          },
          {
            "ep": 11,
            "comments": 14
          },
          {
            "ep": 12,
            "comments": 15
          }
        ]
      }
    },
    {
      "images": {
        "grid": "https://lain.bgm.tv/r/100/pic/cover/l/57/96/268165_qOQsQ.jpg",
        "common": "https://lain.bgm.tv/r/400/pic/cover/l/57/96/268165_qOQsQ.jpg"
      },
      "name": "世話やきキツネの仙狐さん",
      "name_cn": "贤惠幼妻仙狐小姐",
      "infobox": [
        {
          "key": "放送星期",
          "value": "星期三"
        }
      ],
      "rating": {
        "rank": 3579,
        "total": 1890,
        "count": {
          "1": 4,
          "2": 2,
          "3": 5,
          "4": 23,
          "5": 152,
          "6": 501,
          "7": 832,
          "8": 289,
          "9": 50,
          "10": 32
        },
        "score": 6.8
      },
      "total_episodes": 12,
      "collection": {
        "on_hold": 386,
        "dropped": 324,
        "wish": 889,
        "collect": 2939,
        "doing": 394
      },
      "id": 268165,
      "meta_tags": [
        "TV",
        "日本",
        "奇幻",
        "漫画改",
        "日常"
      ],
      "nsfw": false,
      "episodes_summary": {
        "aired_episodes": 12,
        "total_comments": 380,
        "episodes": [
          {
            "ep": 1,
            "comments": 83
          },
          {
            "ep": 2,
            "comments": 54
          },
          {
            "ep": 3,
            "comments": 26
          },
          {
            "ep": 4,
            "comments": 19
          },
          {
            "ep": 5,
            "comments": 33
          },
          {
            "ep": 6,
            "comments": 28
          },
          {
            "ep": 7,
            "comments": 27
          },
          {
            "ep": 8,
            "comments": 18
          },
          {
            "ep": 9,
            "comments": 18
          },
          {
            "ep": 10,
            "comments": 26
          },
          {
            "ep": 11,
            "comments": 21
          },
          {
            "ep": 12,
            "comments": 27
          }
        ]
      }
    },
    {
      "images": {
        "grid": "https://lain.bgm.tv/r/100/pic/cover/l/dc/81/226256_T0771.jpg",
        "common": "https://lain.bgm.tv/r/400/pic/cover/l/dc/81/226256_T0771.jpg"
      },
      "name": "賢者の孫",
      "name_cn": "贤者之孙",
      "infobox": [
        {
          "key": "放送星期",
          "value": "星期三"
        }
      ],
      "rating": {
        "rank": 9168,
        "total": 3395,
        "count": {
          "1": 102,
          "2": 165,
          "3": 388,
          "4": 730,
          "5": 1125,
          "6": 633,
          "7": 183,
          "8": 49,
          "9": 3,
          "10": 17
        },
        "score": 4.7
      },
      "total_episodes": 12,
      "collection": {
        "on_hold": 174,
        "dropped": 661,
        "wish": 261,
        "collect": 5623,
        "doing": 249
      },
      "id": 226256,
      "meta_tags": [
        "TV",
        "日本",
        "奇幻",
        "穿越",
        "小说改"
      ],
      "nsfw": false,
      "episodes_summary": {
        "aired_episodes": 12,
        "total_comments": 338,
        "episodes": [
          {
            "ep": 1,
            "comments": 44
          },
          {
            "ep": 2,
            "comments": 40
          },
          {
            "ep": 3,
            "comments": 32
          },
          {
            "ep": 4,
            "comments": 27
          },
          {
            "ep": 5,
            "comments": 21
          },
          {
            "ep": 6,
            "comments": 45
          },
          {
            "ep": 7,
            "comments": 20
          },
          {
            "ep": 8,
            "comments": 31
          },
          {
            "ep": 9,
            "comments": 16
          },
          {
            "ep": 10,
            "comments": 24
          },
          {
            "ep": 11,
            "comments": 15
          },
          {
            "ep": 12,
            "comments": 23
          }
        ]
      }
    },
    {
      "images": {
        "grid": "https://lain.bgm.tv/r/100/pic/cover/l/50/aa/239912_hCaW2.jpg",
        "common": "https://lain.bgm.tv/r/400/pic/cover/l/50/aa/239912_hCaW2.jpg"
      },
      "name": "キャロル＆チューズデイ",
      "name_cn": "CAROLE & TUESDAY",
      "infobox": [
        {
          "key": "放送星期",
          "value": "星期三"
        }
      ],
      "rating": {
        "rank": 3893,
        "total": 4807,
        "count": {
          "1": 18,
          "2": 20,
          "3": 55,
          "4": 172,
          "5": 454,
          "6": 1183,
          "7": 1635,
          "8": 973,
          "9": 211,
          "10": 86
        },
        "score": 6.7
      },
      "total_episodes": 25,
      "collection": {
        "on_hold": 995,
        "dropped": 969,
        "wish": 1379,
        "collect": 5964,
        "doing": 1194
      },
      "id": 239912,
      "meta_tags": [
        "科幻",
        "TV",
        "日本",
        "原创",
        "音乐"
      ],
      "nsfw": false,
      "episodes_summary": {
        "aired_episodes": 24,
        "total_comments": 1710,
        "episodes": [
          {
            "ep": 1,
            "comments": 175
          },
          {
            "ep": 2,
            "comments": 131
          },
          {
            "ep": 3,
            "comments": 85
          },
          {
            "ep": 4,
            "comments": 101
          },
          {
            "ep": 5,
            "comments": 85
          },
          {
            "ep": 6,
            "comments": 70
          },
          {
            "ep": 7,
            "comments": 72
          },
          {
            "ep": 8,
            "comments": 85
          },
          {
            "ep": 9,
            "comments": 85
          },
          {
            "ep": 10,
            "comments": 66
          },
          {
            "ep": 11,
            "comments": 101
          },
          {
            "ep": 12,
            "comments": 74
          },
          {
            "ep": 13,
            "comments": 51
          },
          {
            "ep": 14,
            "comments": 37
          },
          {
            "ep": 15,
            "comments": 65
          },
          {
            "ep": 16,
            "comments": 38
          },
          {
            "ep": 17,
            "comments": 60
          },
          {
            "ep": 18,
            "comments": 65
          },
          {
            "ep": 19,
            "comments": 39
          },
          {
            "ep": 20,
            "comments": 29
          },
          {
            "ep": 21,
            "comments": 40
          },
          {
            "ep": 22,
            "comments": 46
          },
          {
            "ep": 23,
            "comments": 45
          },
          {
            "ep": 24,
            "comments": 65
          }
        ]
      }
    },
    {
      "images": {
        "grid": "https://lain.bgm.tv/r/100/pic/cover/l/ca/e6/239646_x7BYi.jpg",
        "common": "https://lain.bgm.tv/r/400/pic/cover/l/ca/e6/239646_x7BYi.jpg"
      },
      "name": "さらざんまい",
      "name_cn": "皿三昧",
      "infobox": [
        {
          "key": "放送星期",
          "value": "星期四"
        }
      ],
      "rating": {
        "rank": 2572,
        "total": 3169,
        "count": {
          "1": 10,
          "2": 8,
          "3": 18,
          "4": 49,
          "5": 170,
          "6": 655,
          "7": 1237,
          "8": 816,
          "9": 142,
          "10": 64
        },
        "score": 7
      },
      "total_episodes": 11,
      "collection": {
        "on_hold": 679,
        "dropped": 458,
        "wish": 1671,
        "collect": 4228,
        "doing": 711
      },
      "id": 239646,
      "meta_tags": [
        "TV",
        "日本",
        "奇幻",
        "原创"
      ],
      "nsfw": false,
      "episodes_summary": {
        "aired_episodes": 11,
        "total_comments": 1195,
        "episodes": [
          {
            "ep": 1,
            "comments": 187
          },
          {
            "ep": 2,
            "comments": 138
          },
          {
            "ep": 3,
            "comments": 106
          },
          {
            "ep": 4,
            "comments": 86
          },
          {
            "ep": 5,
            "comments": 106
          },
          {
            "ep": 6,
            "comments": 103
          },
          {
            "ep": 7,
            "comments": 99
          },
          {
            "ep": 8,
            "comments": 92
          },
          {
            "ep": 9,
            "comments": 89
          },
          {
            "ep": 10,
            "comments": 86
          },
          {
            "ep": 11,
            "comments": 103
          }
        ]
      }
    },
    {
      "images": {
        "grid": "https://lain.bgm.tv/r/100/pic/cover/l/d2/ca/254762_vmbVB.jpg",
        "common": "https://lain.bgm.tv/r/400/pic/cover/l/d2/ca/254762_vmbVB.jpg"
      },
      "name": "文豪ストレイドッグス 第3シーズン",
      "name_cn": "文豪野犬 第三季",
      "infobox": [
        {
          "key": "放送星期",
          "value": "星期五"
        }
      ],
      "rating": {
        "rank": 3211,
        "total": 2553,
        "count": {
          "1": 3,
          "2": 2,
          "3": 13,
          "4": 40,
          "5": 159,
          "6": 610,
          "7": 1147,
          "8": 479,
          "9": 48,
          "10": 52
        },
        "score": 6.8
      },
      "total_episodes": 12,
      "collection": {
        "on_hold": 147,
        "dropped": 116,
        "wish": 594,
        "collect": 4817,
        "doing": 223
      },
      "id": 254762,
      "meta_tags": [
        "TV",
        "日本",
        "奇幻",
        "漫画改",
        "战斗"
      ],
      "nsfw": false,
      "episodes_summary": {
        "aired_episodes": 12,
        "total_comments": 191,
        "episodes": [
          {
            "ep": 1,
            "comments": 21
          },
          {
            "ep": 2,
            "comments": 12
          },
          {
            "ep": 3,
            "comments": 20
          },
          {
            "ep": 4,
            "comments": 15
          },
          {
            "ep": 5,
            "comments": 12
          },
          {
            "ep": 6,
            "comments": 18
          },
          {
            "ep": 7,
            "comments": 20
          },
          {
            "ep": 8,
            "comments": 9
          },
          {
            "ep": 9,
            "comments": 13
          },
          {
            "ep": 10,
            "comments": 18
          },
          {
            "ep": 11,
            "comments": 19
          },
          {
            "ep": 12,
            "comments": 14
          }
        ]
      }
    },
    {
      "images": {
        "grid": "https://lain.bgm.tv/r/100/pic/cover/l/c0/de/217573_trel5.jpg",
        "common": "https://lain.bgm.tv/r/400/pic/cover/l/c0/de/217573_trel5.jpg"
      },
      "name": "リラックマとカオルさん",
      "name_cn": "轻松小熊和小薰",
      "infobox": [],
      "rating": {
        "rank": 1837,
        "total": 124,
        "count": {
          "1": 1,
          "2": 0,
          "3": 1,
          "4": 2,
          "5": 7,
          "6": 13,
          "7": 44,
          "8": 47,
          "9": 4,
          "10": 5
        },
        "score": 7.2
      },
      "total_episodes": 13,
      "collection": {
        "on_hold": 14,
        "dropped": 32,
        "wish": 133,
        "collect": 189,
        "doing": 21
      },
      "id": 217573,
      "meta_tags": [
        "原创",
        "WEB"
      ],
      "nsfw": false,
      "episodes_summary": {
        "aired_episodes": 13,
        "total_comments": 41,
        "episodes": [
          {
            "ep": 1,
            "comments": 4
          },
          {
            "ep": 2,
            "comments": 1
          },
          {
            "ep": 3,
            "comments": 8
          },
          {
            "ep": 4,
            "comments": 2
          },
          {
            "ep": 5,
            "comments": 3
          },
          {
            "ep": 6,
            "comments": 3
          },
          {
            "ep": 7,
            "comments": 1
          },
          {
            "ep": 8,
            "comments": 5
          },
          {
            "ep": 9,
            "comments": 3
          },
          {
            "ep": 10,
            "comments": 3
          },
          {
            "ep": 11,
            "comments": 2
          },
          {
            "ep": 12,
            "comments": 2
          },
          {
            "ep": 13,
            "comments": 4
          }
        ]
      }
    },
    {
      "images": {
        "grid": "https://lain.bgm.tv/r/100/pic/cover/l/c2/56/263750_56TBs.jpg",
        "common": "https://lain.bgm.tv/r/400/pic/cover/l/c2/56/263750_56TBs.jpg"
      },
      "name": "進撃の巨人 Season 3 Part.2",
      "name_cn": "进击的巨人 第三季 Part.2",
      "infobox": [
        {
          "key": "放送星期",
          "value": "星期日"
        }
      ],
      "rating": {
        "rank": 22,
        "total": 18882,
        "count": {
          "1": 141,
          "2": 22,
          "3": 33,
          "4": 41,
          "5": 113,
          "6": 364,
          "7": 1320,
          "8": 4865,
          "9": 6961,
          "10": 5022
        },
        "score": 8.7
      },
      "total_episodes": 10,
      "collection": {
        "on_hold": 304,
        "dropped": 272,
        "wish": 1614,
        "collect": 30603,
        "doing": 671
      },
      "id": 263750,
      "meta_tags": [
        "TV",
        "日本",
        "奇幻",
        "漫画改",
        "战斗"
      ],
      "nsfw": false,
      "episodes_summary": {
        "aired_episodes": 10,
        "total_comments": 1839,
        "episodes": [
          {
            "ep": 1,
            "comments": 148
          },
          {
            "ep": 2,
            "comments": 129
          },
          {
            "ep": 3,
            "comments": 162
          },
          {
            "ep": 4,
            "comments": 199
          },
          {
            "ep": 5,
            "comments": 217
          },
          {
            "ep": 6,
            "comments": 304
          },
          {
            "ep": 7,
            "comments": 159
          },
          {
            "ep": 8,
            "comments": 192
          },
          {
            "ep": 9,
            "comments": 185
          },
          {
            "ep": 10,
            "comments": 144
          }
        ]
      }
    },
    {
      "images": {
        "grid": "https://lain.bgm.tv/r/100/pic/cover/l/4f/e2/267412_XsOB3.jpg",
        "common": "https://lain.bgm.tv/r/400/pic/cover/l/4f/e2/267412_XsOB3.jpg"
      },
      "name": "機動戦士ガンダム THE ORIGIN 前夜 赤い彗星",
      "name_cn": "机动战士高达 THE ORIGIN 前夜 红色彗星",
      "infobox": [
        {
          "key": "放送星期",
          "value": "星期日"
        }
      ],
      "rating": {
        "rank": 862,
        "total": 579,
        "count": {
          "1": 1,
          "2": 1,
          "3": 2,
          "4": 0,
          "5": 12,
          "6": 50,
          "7": 195,
          "8": 250,
          "9": 46,
          "10": 22
        },
        "score": 7.5
      },
      "total_episodes": 13,
      "collection": {
        "on_hold": 35,
        "dropped": 44,
        "wish": 319,
        "collect": 1087,
        "doing": 43
      },
      "id": 267412,
      "meta_tags": [
        "TV",
        "日本",
        "原创"
      ],
      "nsfw": false,
      "episodes_summary": {
        "aired_episodes": 13,
        "total_comments": 32,
        "episodes": [
          {
            "ep": 1,
            "comments": 4
          },
          {
            "ep": 2,
            "comments": 2
          },
          {
            "ep": 3,
            "comments": 1
          },
          {
            "ep": 4,
            "comments": 1
          },
          {
            "ep": 5,
            "comments": 3
          },
          {
            "ep": 6,
            "comments": 2
          },
          {
            "ep": 7,
            "comments": 2
          },
          {
            "ep": 8,
            "comments": 3
          },
          {
            "ep": 9,
            "comments": 3
          },
          {
            "ep": 10,
            "comments": 2
          },
          {
            "ep": 11,
            "comments": 3
          },
          {
            "ep": 12,
            "comments": 2
          },
          {
            "ep": 13,
            "comments": 4
          }
        ]
      }
    },
    {
      "images": {
        "grid": "https://lain.bgm.tv/r/100/pic/cover/l/f1/7d/270294_5ybVy.jpg",
        "common": "https://lain.bgm.tv/r/400/pic/cover/l/f1/7d/270294_5ybVy.jpg"
      },
      "name": "みるタイツ",
      "name_cn": "裤袜视界",
      "infobox": [
        {
          "key": "放送星期",
          "value": "星期六"
        }
      ],
      "rating": {
        "rank": 4967,
        "total": 2473,
        "count": {
          "1": 10,
          "2": 15,
          "3": 29,
          "4": 76,
          "5": 267,
          "6": 762,
          "7": 896,
          "8": 293,
          "9": 61,
          "10": 64
        },
        "score": 6.5
      },
      "total_episodes": 13,
      "collection": {
        "on_hold": 190,
        "dropped": 155,
        "wish": 1050,
        "collect": 3994,
        "doing": 299
      },
      "id": 270294,
      "meta_tags": [
        "百合",
        "原创",
        "WEB"
      ],
      "nsfw": false,
      "episodes_summary": {
        "aired_episodes": 12,
        "total_comments": 533,
        "episodes": [
          {
            "ep": 1,
            "comments": 46
          },
          {
            "ep": 2,
            "comments": 53
          },
          {
            "ep": 3,
            "comments": 43
          },
          {
            "ep": 4,
            "comments": 32
          },
          {
            "ep": 5,
            "comments": 40
          },
          {
            "ep": 6,
            "comments": 19
          },
          {
            "ep": 7,
            "comments": 110
          },
          {
            "ep": 8,
            "comments": 67
          },
          {
            "ep": 9,
            "comments": 32
          },
          {
            "ep": 10,
            "comments": 44
          },
          {
            "ep": 11,
            "comments": 29
          },
          {
            "ep": 12,
            "comments": 18
          }
        ]
      }
    },
    {
      "images": {
        "grid": "https://lain.bgm.tv/r/100/pic/cover/l/3a/7f/233926_V09ek.jpg",
        "common": "https://lain.bgm.tv/r/400/pic/cover/l/3a/7f/233926_V09ek.jpg"
      },
      "name": "続・終物語",
      "name_cn": "续·终物语",
      "infobox": [],
      "rating": {
        "rank": 304,
        "total": 4959,
        "count": {
          "1": 2,
          "2": 0,
          "3": 0,
          "4": 12,
          "5": 50,
          "6": 238,
          "7": 1183,
          "8": 2437,
          "9": 679,
          "10": 358
        },
        "score": 7.9
      },
      "total_episodes": 6,
      "collection": {
        "on_hold": 178,
        "dropped": 43,
        "wish": 1845,
        "collect": 8304,
        "doing": 265
      },
      "id": 233926,
      "meta_tags": [
        "剧场版",
        "后宫",
        "日本",
        "奇幻",
        "小说改"
      ],
      "nsfw": false,
      "episodes_summary": {
        "aired_episodes": 6,
        "total_comments": 203,
        "episodes": [
          {
            "ep": 1,
            "comments": 35
          },
          {
            "ep": 2,
            "comments": 36
          },
          {
            "ep": 3,
            "comments": 20
          },
          {
            "ep": 4,
            "comments": 27
          },
          {
            "ep": 5,
            "comments": 34
          },
          {
            "ep": 6,
            "comments": 51
          }
        ]
      }
    }
  ],
  "last_update_time": "2025-06-05T03:57:23.409936"
}